heimarobot/__init__.py
heimarobot/face_attribute.py
heimarobot/face_detection.py
heimarobot/face_landmark.py
heimarobot/face_recognition.py
heimarobot/face_swapper.py
heimarobot/utils.py
heimarobot/insightface/__init__.py
heimarobot/insightface/app/__init__.py
heimarobot/insightface/app/common.py
heimarobot/insightface/app/face_analysis.py
heimarobot/insightface/app/mask_renderer.py
heimarobot/insightface/commands/__init__.py
heimarobot/insightface/commands/insightface_cli.py
heimarobot/insightface/commands/model_download.py
heimarobot/insightface/commands/rec_add_mask_param.py
heimarobot/insightface/data/__init__.py
heimarobot/insightface/data/image.py
heimarobot/insightface/data/pickle_object.py
heimarobot/insightface/data/rec_builder.py
heimarobot/insightface/data/images/Tom_Hanks_54745.png
heimarobot/insightface/data/images/mask_black.jpg
heimarobot/insightface/data/images/mask_blue.jpg
heimarobot/insightface/data/images/mask_green.jpg
heimarobot/insightface/data/images/mask_white.jpg
heimarobot/insightface/data/images/t1.jpg
heimarobot/insightface/data/objects/meanshape_68.pkl
heimarobot/insightface/model_zoo/__init__.py
heimarobot/insightface/model_zoo/arcface_onnx.py
heimarobot/insightface/model_zoo/attribute.py
heimarobot/insightface/model_zoo/inswapper.py
heimarobot/insightface/model_zoo/landmark.py
heimarobot/insightface/model_zoo/model_store.py
heimarobot/insightface/model_zoo/model_zoo.py
heimarobot/insightface/model_zoo/retinaface.py
heimarobot/insightface/model_zoo/scrfd.py
heimarobot/insightface/thirdparty/__init__.py
heimarobot/insightface/thirdparty/face3d/__init__.py
heimarobot/insightface/thirdparty/face3d/mesh/__init__.py
heimarobot/insightface/thirdparty/face3d/mesh/io.py
heimarobot/insightface/thirdparty/face3d/mesh/light.py
heimarobot/insightface/thirdparty/face3d/mesh/render.py
heimarobot/insightface/thirdparty/face3d/mesh/transform.py
heimarobot/insightface/thirdparty/face3d/mesh/vis.py
robotpipe-0.0.4.dist-info/METADATA
robotpipe-0.0.4.dist-info/WHEEL
robotpipe-0.0.4.dist-info/entry_points.txt
robotpipe-0.0.4.dist-info/top_level.txt
robotpipe-0.0.4.dist-info/zip-safe
robotpipe-0.0.4.dist-info/RECORD
