Metadata-Version: 2.1
Name: robotpipe
Version: 0.0.4
Summary: robotpipe Python Library
Home-page: https://github.com/xiaokaijun/robotpipe
Author: robotpipe Contributors
Author-email: xiaokaijun5027@163.com
License: MIT
Requires-Dist: numpy
Requires-Dist: onnx
Requires-Dist: tqdm
Requires-Dist: requests
Requires-Dist: matplotlib
Requires-Dist: Pillow
Requires-Dist: scipy
Requires-Dist: scikit-learn
Requires-Dist: scikit-image
Requires-Dist: easydict
Requires-Dist: cython
Requires-Dist: albumentations
Requires-Dist: prettytable
